cyj_test/__init__.py
cyj_test/python39/_pyxgdb.cpython-39-x86_64-linux-gnu.so
cyj_test-0.0.10.data/data/_pyxgdb.cpython-39-x86_64-linux-gnu.so
cyj_test-0.0.10.dist-info/METADATA
cyj_test-0.0.10.dist-info/WHEEL
cyj_test-0.0.10.dist-info/top_level.txt
cyj_test-0.0.10.dist-info/RECORD
