Metadata-Version: 2.1
Name: cyj_test
Version: 0.0.10
Summary: A description of cyj package
Home-page: UNKNOWN
Author: yinchenjue
Author-email: 454194347@qq.com
License: UNKNOWN
Platform: UNKNOWN
Requires-Python: >=3.6
